{
  "execId": 25,
  "time": 0.69453,
  "dotName": "apex7_k3",
  "dotPath": "/home/jeronimo/GIT/PeR/benchmarks/fpga/bench_test/apex7_k3.dot",
  "placer": "yoto",
  "tries": 4162,
  "swaps": 108,
  "edgesAlgorithm": "DEPTH_FIRST",
  "totalCost": 2770,
  "placement": [-1, 18, 24, 61, 34, 37, 67, 46, 143, 3, 5, 135, 92, 146, 16, 48, 105, -1, 27, -1, 145, -1, 8, -1, 15, 79, 110, -1, 73, -1, -1, -1, -1, 13, 58, 118, 112, 19, -1, -1, -1, -1, -1, -1, -1, 55, -1, -1, -1, -1, -1, -1, -1, 87, 7, 14, 40, -1, -1, -1, -1, -1, -1, -1, 32, -1, -1, -1, -1, -1, -1, -1, -1, -1, -1, -1, -1, -1, -1, -1, -1, -1, 56, 95, 44, -1, -1, -1, -1, -1, -1, -1, -1, -1, -1, -1, -1, -1, -1, -1, -1, -1, -1, -1, -1, -1, -1, -1, -1, -1, -1, 91, 53, -1, -1, -1, -1, -1, -1, -1, -1, -1, -1, -1, -1, -1, -1, -1, -1, -1, -1, -1, -1, -1, -1, -1, 114, -1, 77, 43, 11, -1, -1, -1, -1, -1, -1, -1, -1, -1, -1, -1, -1, -1, -1, -1, -1, -1, -1, -1, -1, -1, -1, -1, -1, 75, 54, 76, 111, -1, -1, -1, -1, -1, -1, -1, -1, -1, -1, -1, -1, -1, -1, -1, -1, -1, -1, -1, -1, -1, -1, -1, -1, -1, 28, 71, 68, -1, -1, -1, -1, -1, -1, -1, -1, -1, -1, -1, -1, -1, -1, -1, -1, -1, -1, -1, -1, -1, -1, -1, -1, -1, -1, 124, 100, 80, -1, -1, -1, -1, -1, -1, -1, -1, -1, -1, -1, -1, -1, -1, -1, -1, -1, -1, -1, -1, -1, -1, -1, 125, -1, 127, 65, -1, 139, -1, -1, -1, -1, -1, -1, -1, -1, -1, -1, -1, -1, -1, -1, -1, -1, -1, -1, -1, -1, -1, -1, -1, -1, 141, 35, 6, -1, -1, -1, -1, -1, -1, -1, -1, -1, -1, -1, -1, -1, -1, -1, -1, -1, -1, -1, -1, -1, -1, -1, -1, -1, 78, 107, -1, -1, -1, -1, -1, -1, -1, -1, -1, -1, -1, -1, -1, -1, -1, -1, -1, -1, -1, -1, -1, -1, -1, -1, 12, -1, 23, -1, -1, -1, -1, -1, -1, -1, -1, -1, -1, -1, -1, -1, -1, -1, -1, -1, -1, -1, -1, -1, -1, -1, -1, -1, -1, 86, 62, 115, 89, -1, -1, -1, -1, -1, -1, -1, -1, -1, -1, -1, -1, -1, -1, -1, -1, -1, -1, -1, -1, -1, -1, -1, -1, -1, -1, 134, -1, -1, -1, -1, -1, -1, -1, -1, -1, -1, -1, -1, -1, -1, -1, -1, -1, -1, -1, -1, -1, -1, -1, -1, -1, -1, -1, 82, -1, -1, -1, -1, -1, -1, -1, -1, -1, -1, -1, -1, -1, -1, -1, -1, -1, -1, -1, -1, -1, -1, -1, -1, -1, -1, 29, 113, -1, -1, -1, -1, -1, -1, -1, -1, -1, -1, -1, -1, -1, -1, -1, -1, -1, -1, -1, -1, -1, -1, -1, -1, -1, -1, 47, 36, -1, -1, -1, -1, -1, -1, -1, -1, -1, -1, -1, -1, -1, -1, -1, -1, -1, -1, -1, -1, -1, -1, -1, 60, -1, -1, 102, 22, -1, -1, -1, -1, -1, -1, -1, -1, -1, -1, -1, -1, -1, -1, -1, -1, -1, -1, -1, -1, -1, -1, -1, -1, 66, -1, 85, 104, -1, -1, -1, -1, -1, -1, -1, -1, -1, -1, -1, -1, -1, -1, -1, -1, -1, -1, -1, -1, -1, -1, -1, -1, -1, -1, 4, 0, -1, -1, -1, -1, -1, -1, -1, -1, -1, -1, -1, -1, -1, -1, -1, -1, -1, -1, -1, -1, -1, -1, -1, -1, -1, 59, 2, 9, -1, -1, -1, -1, -1, -1, -1, -1, -1, -1, -1, -1, -1, -1, -1, -1, -1, -1, -1, -1, -1, -1, -1, -1, -1, 81, 123, 121, -1, -1, -1, -1, -1, -1, -1, -1, -1, -1, -1, -1, -1, -1, -1, -1, -1, -1, -1, -1, -1, -1, -1, -1, 137, 138, 49, 26, -1, -1, -1, -1, -1, -1, -1, -1, -1, -1, -1, -1, -1, -1, -1, -1, -1, -1, -1, -1, -1, -1, -1, -1, 25, 101, 136, 97, 30, -1, -1, -1, 117, -1, -1, -1, -1, -1, -1, -1, -1, -1, -1, -1, -1, -1, -1, -1, -1, -1, -1, -1, 88, -1, 126, 38, -1, -1, -1, 64, 17, 109, -1, -1, -1, -1, -1, -1, -1, -1, -1, -1, 103, -1, -1, -1, 1, -1, -1, -1, -1, -1, 106, 90, -1, -1, -1, 45, 39, 144, 51, 129, 98, 84, 133, -1, -1, -1, -1, -1, -1, 130, -1, -1, -1, 119, -1, 128, -1, 122, 93, -1, 132, 50, 52, 57, 131, 20, 74, 120, 31, 63, 10, 21, 96, 140, 99, 70, 116, 108, 33, 69, 42, 72, 142, 83, 41, 94, -1],
  "n2c": [560, 721, 587, 9, 559, 10, 281, 54, 22, 588, 767, 140, 333, 33, 55, 24, 14, 705, 1, 37, 762, 768, 504, 335, 2, 669, 644, 18, 194, 447, 673, 765, 64, 775, 4, 280, 476, 5, 700, 733, 56, 781, 777, 139, 84, 732, 7, 475, 15, 643, 758, 735, 759, 112, 166, 45, 82, 760, 34, 586, 500, 3, 363, 766, 704, 252, 529, 6, 196, 776, 772, 195, 778, 28, 763, 165, 167, 138, 307, 25, 225, 614, 420, 780, 738, 531, 362, 53, 697, 365, 728, 111, 12, 755, 782, 83, 769, 672, 737, 771, 224, 670, 503, 717, 532, 16, 727, 308, 774, 706, 26, 168, 36, 448, 136, 364, 773, 677, 35, 750, 764, 616, 754, 615, 223, 249, 699, 251, 752, 736, 746, 761, 757, 739, 392, 11, 671, 641, 642, 254, 770, 279, 779, 8, 734, 20, 13]
}
