{
  "execId": 10,
  "time": 0.21136,
  "dotName": "term1_k4",
  "dotPath": "/home/jeronimo/GIT/PeR/benchmarks/fpga/bench_test/term1_k4.dot",
  "placer": "yoto",
  "tries": 1278,
  "swaps": 57,
  "edgesAlgorithm": "DEPTH_FIRST",
  "totalCost": 694,
  "placement": [-1, 42, 66, 31, 24, 41, 83, 55, 22, 29, 79, 13, 61, 81, -1, 51, 48, -1, -1, 37, 18, 27, 43, 4, -1, 21, 8, 38, 80, 14, 45, 84, -1, -1, -1, -1, 87, -1, -1, -1, -1, 56, -1, 50, 46, 77, 9, 32, -1, -1, 74, -1, -1, -1, -1, -1, -1, -1, -1, 65, 5, 62, 1, -1, -1, -1, -1, -1, -1, -1, -1, -1, -1, -1, 2, 20, 72, 67, -1, -1, -1, -1, -1, -1, -1, -1, -1, -1, 64, -1, 60, 3, -1, -1, -1, -1, -1, -1, -1, -1, -1, -1, -1, -1, -1, 11, 73, -1, -1, -1, -1, -1, -1, -1, -1, -1, -1, -1, -1, -1, 68, 25, -1, -1, -1, -1, -1, -1, -1, -1, -1, -1, -1, -1, 49, 26, 34, 7, -1, -1, -1, -1, -1, -1, -1, -1, -1, -1, 33, 57, 76, 12, 52, -1, -1, -1, -1, -1, -1, -1, -1, -1, -1, -1, 47, 19, 39, 63, -1, -1, -1, -1, -1, -1, -1, -1, -1, -1, -1, 75, 15, 86, 53, 82, -1, 70, -1, -1, -1, 0, -1, -1, -1, -1, 54, 23, 16, -1, -1, -1, -1, -1, -1, 85, 78, -1, -1, -1, -1, 44, -1, 58, 17, 35, 71, 36, 6, 10, 59, 69, 28, 40, -1, 30, -1],
  "n2c": [189, 62, 74, 91, 23, 60, 216, 137, 26, 46, 217, 105, 151, 11, 29, 180, 196, 212, 20, 165, 75, 25, 8, 195, 4, 121, 135, 21, 220, 9, 223, 3, 47, 148, 136, 213, 215, 19, 27, 166, 221, 5, 1, 22, 209, 30, 44, 164, 16, 134, 43, 15, 152, 182, 194, 7, 41, 149, 211, 218, 90, 12, 61, 167, 88, 59, 2, 77, 120, 219, 185, 214, 76, 106, 50, 179, 150, 45, 204, 10, 28, 13, 183, 6, 31, 203, 181, 36]
}
