{
  "execId": 78,
  "time": 0.278629,
  "dotName": "term1_k5",
  "dotPath": "/home/jeronimo/GIT/PeR/benchmarks/fpga/bench_test/term1_k5.dot",
  "placer": "yoto",
  "tries": 1041,
  "swaps": 47,
  "edgesAlgorithm": "DEPTH_FIRST",
  "totalCost": 681,
  "placement": [-1, -1, 20, 36, 21, 63, 53, 19, 17, 79, 44, 50, 72, 67, 51, -1, 15, -1, 34, 57, -1, -1, 2, 9, 8, 6, -1, -1, 24, 43, -1, 55, 48, 71, -1, -1, -1, -1, 4, -1, 70, -1, -1, -1, -1, 54, -1, 18, 3, -1, -1, -1, -1, -1, -1, -1, -1, -1, -1, -1, -1, -1, -1, 39, 80, 25, -1, -1, -1, -1, -1, -1, -1, -1, -1, -1, -1, -1, 78, -1, 61, 35, -1, -1, -1, -1, -1, -1, -1, -1, -1, -1, -1, 0, 49, -1, 68, 1, 29, -1, -1, -1, -1, -1, -1, -1, -1, -1, -1, -1, 60, 77, 5, 10, 11, -1, -1, -1, -1, -1, -1, -1, -1, -1, -1, -1, -1, 37, 45, 46, 75, -1, -1, -1, -1, -1, -1, -1, -1, -1, -1, -1, -1, -1, 23, 7, -1, -1, -1, -1, -1, -1, -1, -1, -1, -1, -1, -1, -1, -1, 38, 69, -1, -1, -1, -1, -1, -1, -1, -1, -1, -1, -1, -1, -1, 58, 62, 30, -1, -1, -1, -1, -1, -1, -1, -1, -1, -1, -1, -1, -1, -1, 13, 73, -1, -1, -1, -1, -1, -1, -1, -1, -1, -1, -1, -1, -1, 14, 28, -1, -1, -1, -1, -1, -1, -1, -1, -1, -1, -1, -1, -1, -1, 33, 12, 66, 22, -1, -1, -1, 16, -1, -1, -1, -1, -1, -1, -1, -1, 74, -1, 32, 76, 52, 41, 64, 31, 40, 42, 27, 59, 47, 56, 26, 65, -1],
  "n2c": [93, 97, 22, 48, 38, 112, 25, 145, 24, 23, 113, 114, 224, 192, 207, 16, 230, 8, 47, 7, 2, 4, 226, 144, 28, 65, 253, 249, 208, 98, 177, 246, 241, 223, 18, 81, 3, 127, 160, 63, 247, 244, 248, 29, 10, 128, 129, 251, 32, 94, 11, 14, 243, 6, 45, 31, 252, 19, 175, 250, 110, 80, 176, 5, 245, 254, 225, 13, 96, 161, 40, 33, 12, 193, 239, 130, 242, 111, 78, 9, 64]
}
