{
  "execId": 43,
  "time": 0.307226,
  "dotName": "term1_k4",
  "dotPath": "/home/jeronimo/GIT/PeR/benchmarks/fpga/bench_test/term1_k4.dot",
  "placer": "yoto",
  "tries": 3105,
  "swaps": 57,
  "edgesAlgorithm": "DEPTH_FIRST",
  "totalCost": 583,
  "placement": [-1, 13, 23, 45, 65, 51, 22, 30, 58, 41, 36, 11, 59, 10, -1, 54, 16, -1, -1, -1, -1, -1, 4, 78, 85, 9, 21, -1, -1, 19, 47, 50, 25, -1, -1, -1, -1, -1, 82, 84, -1, -1, -1, -1, 29, 76, 80, -1, -1, -1, -1, -1, -1, -1, -1, -1, -1, -1, -1, 77, 49, -1, -1, -1, -1, -1, -1, -1, -1, -1, -1, -1, -1, 18, 6, 17, 48, -1, -1, -1, -1, -1, -1, -1, -1, -1, -1, 87, 27, 75, 68, -1, -1, -1, -1, -1, -1, -1, -1, -1, -1, -1, 74, 43, 35, 69, 70, -1, -1, -1, -1, -1, -1, -1, -1, -1, -1, 3, -1, 20, 57, 38, -1, -1, -1, -1, -1, -1, -1, -1, -1, -1, -1, 32, 42, 24, 34, -1, -1, -1, -1, -1, -1, -1, -1, -1, -1, -1, -1, 14, 79, 8, 64, -1, -1, -1, -1, -1, -1, -1, -1, 73, -1, 56, -1, 83, -1, -1, -1, -1, -1, -1, -1, -1, -1, -1, 12, -1, -1, 15, 81, -1, -1, -1, -1, -1, 37, -1, -1, -1, 53, 86, 72, 0, -1, 28, -1, -1, 62, -1, 67, -1, 39, -1, 52, 7, 63, 1, 33, 55, -1, 44, 61, 66, 26, 60, 5, 46, 31, 71, -1, -1, 40, 2, -1],
  "n2c": [193, 207, 223, 117, 22, 216, 74, 205, 151, 25, 13, 11, 176, 1, 149, 179, 16, 75, 73, 29, 119, 26, 6, 2, 135, 32, 214, 88, 195, 44, 7, 218, 133, 208, 136, 104, 10, 186, 121, 202, 222, 9, 134, 103, 211, 3, 217, 30, 76, 60, 31, 5, 204, 190, 15, 209, 163, 120, 8, 12, 215, 212, 198, 206, 152, 4, 213, 200, 90, 105, 106, 219, 192, 161, 102, 89, 45, 59, 23, 150, 46, 180, 38, 165, 39, 24, 191, 87]
}
