{
  "execId": 46,
  "time": 0.543474,
  "dotName": "apex7_k4",
  "dotPath": "/home/jeronimo/GIT/PeR/benchmarks/fpga/bench_test/apex7_k4.dot",
  "placer": "yoto",
  "tries": 3313,
  "swaps": 79,
  "edgesAlgorithm": "DEPTH_FIRST",
  "totalCost": 1896,
  "placement": [-1, 97, 1, 85, 109, 6, 107, 117, 24, 35, 43, 58, 12, 51, 9, 66, 96, 83, 103, 62, 94, 81, 49, -1, 63, -1, 106, 118, -1, -1, -1, -1, -1, -1, -1, -1, -1, -1, -1, -1, -1, -1, -1, -1, 38, 26, 116, 18, 101, -1, 11, 45, -1, -1, -1, -1, -1, -1, -1, -1, -1, -1, -1, -1, -1, -1, -1, -1, -1, -1, -1, 114, 48, -1, -1, 14, -1, -1, -1, -1, -1, -1, -1, -1, -1, -1, -1, -1, -1, -1, -1, -1, -1, -1, 112, 41, 61, -1, -1, -1, -1, -1, -1, -1, -1, -1, -1, -1, -1, -1, -1, -1, -1, -1, -1, -1, -1, -1, -1, 30, 0, -1, -1, -1, -1, -1, -1, -1, -1, -1, -1, -1, -1, -1, -1, -1, -1, -1, -1, -1, -1, -1, -1, 59, 69, -1, -1, -1, -1, -1, -1, -1, -1, -1, -1, -1, -1, -1, -1, -1, -1, -1, -1, 108, 22, 77, -1, 37, 73, -1, -1, -1, -1, -1, -1, -1, -1, -1, -1, -1, -1, -1, -1, -1, -1, -1, -1, -1, 42, -1, 87, 13, 92, -1, -1, -1, -1, -1, -1, -1, -1, -1, -1, -1, -1, -1, -1, -1, -1, -1, -1, -1, -1, 105, -1, 5, 104, -1, -1, -1, -1, -1, -1, -1, -1, -1, -1, -1, -1, -1, -1, -1, -1, -1, -1, -1, -1, -1, -1, 55, 40, -1, -1, -1, -1, -1, -1, -1, -1, -1, -1, -1, -1, -1, -1, -1, -1, -1, -1, -1, -1, -1, -1, 20, 33, -1, -1, -1, -1, -1, -1, -1, -1, -1, -1, -1, -1, -1, -1, -1, -1, -1, -1, -1, -1, -1, 36, 50, 47, -1, -1, -1, -1, -1, -1, -1, -1, -1, -1, -1, -1, -1, -1, -1, -1, -1, -1, -1, -1, -1, -1, 34, 70, 60, -1, -1, -1, -1, -1, -1, -1, -1, -1, -1, -1, -1, -1, -1, -1, -1, -1, -1, -1, -1, -1, 79, 100, -1, -1, -1, -1, -1, -1, -1, -1, -1, -1, -1, -1, -1, -1, -1, -1, -1, -1, -1, -1, -1, -1, 65, 68, -1, -1, -1, -1, -1, -1, -1, -1, -1, -1, -1, -1, -1, -1, -1, -1, -1, -1, -1, -1, -1, -1, 90, 2, -1, -1, -1, -1, -1, -1, -1, -1, -1, -1, -1, -1, -1, -1, -1, -1, -1, -1, -1, -1, -1, -1, 31, 76, 93, -1, -1, -1, -1, -1, -1, -1, -1, -1, -1, -1, -1, -1, -1, -1, -1, -1, -1, -1, -1, -1, 57, 46, 84, -1, -1, -1, -1, -1, -1, -1, -1, -1, -1, -1, -1, -1, -1, -1, -1, -1, -1, -1, -1, -1, 7, 3, 56, -1, -1, -1, -1, -1, -1, -1, -1, -1, -1, -1, -1, -1, -1, -1, -1, -1, -1, -1, -1, -1, 16, 54, -1, -1, -1, -1, -1, 82, -1, -1, -1, -1, -1, -1, -1, -1, -1, -1, -1, -1, -1, -1, -1, -1, -1, 21, -1, -1, -1, -1, 91, -1, 28, -1, -1, -1, 113, 75, -1, -1, -1, -1, -1, -1, -1, -1, -1, -1, 86, 110, -1, -1, -1, 115, 4, 52, -1, -1, -1, 25, 23, 88, 98, -1, -1, -1, -1, -1, -1, -1, -1, -1, 19, -1, 53, 71, 67, 64, 89, 8, 72, 15, 102, 29, 99, 39, 17, 32, 27, 95, 44, 10, 74, 80, 78, 111, -1],
  "n2c": [120, 2, 384, 456, 533, 215, 5, 455, 558, 14, 570, 50, 12, 191, 75, 560, 479, 565, 47, 551, 263, 504, 164, 539, 8, 538, 45, 567, 511, 562, 119, 407, 566, 264, 311, 9, 286, 167, 44, 564, 240, 95, 188, 10, 569, 51, 432, 288, 72, 22, 287, 13, 534, 553, 480, 239, 457, 431, 11, 143, 313, 96, 19, 24, 556, 359, 15, 555, 360, 144, 312, 554, 559, 168, 571, 516, 408, 165, 573, 335, 572, 21, 486, 17, 433, 3, 527, 190, 540, 557, 383, 509, 192, 409, 20, 568, 16, 1, 541, 563, 336, 48, 561, 18, 216, 213, 26, 6, 163, 4, 528, 574, 94, 515, 71, 532, 46, 7, 27]
}
