{
  "time": 0.056152,
  "dotName": "apex7_k6",
  "dotPath": "/home/jeronimo/GIT/PeR/benchmarks/fpga/eval/apex7_k6.dot",
  "placer": "yotoBase",
  "cacheMisses": 0,
  "tries": 8187,
  "swaps": 91,
  "edgesAlgorithm": "DEPTH_FIRST",
  "totalCost": 8,
  "placement": [-1, 99, 70, 33, 42, 17, 14, 119, 8, 104, 47, -1, 132, 121, 4, 48, 77, 80, 2, 85, 91, 136, 60, -1, 139, -1, 109, 44, -1, -1, 102, -1, -1, 101, -1, -1, -1, -1, -1, -1, 115, 122, 35, 133, 41, 86, -1, 32, 45, -1, -1, 59, -1, -1, -1, -1, -1, -1, -1, -1, -1, -1, -1, -1, -1, -1, 58, 49, 138, -1, -1, 5, 120, -1, -1, -1, -1, -1, -1, -1, -1, -1, -1, -1, -1, -1, -1, -1, -1, -1, -1, 117, -1, -1, -1, 127, 68, -1, -1, -1, -1, -1, -1, -1, -1, -1, -1, -1, -1, -1, -1, -1, -1, -1, -1, -1, -1, -1, -1, -1, 98, -1, -1, -1, -1, -1, -1, -1, -1, -1, -1, -1, -1, -1, -1, -1, -1, -1, -1, -1, -1, -1, -1, -1, 129, -1, -1, -1, -1, -1, -1, -1, -1, -1, -1, -1, -1, -1, -1, -1, -1, -1, -1, -1, -1, -1, -1, 22, 6, -1, -1, -1, -1, -1, -1, -1, -1, -1, -1, -1, -1, -1, -1, -1, -1, -1, -1, -1, -1, -1, -1, 71, 83, 31, -1, -1, -1, -1, -1, -1, -1, -1, -1, -1, -1, -1, -1, -1, -1, -1, -1, -1, -1, -1, -1, 9, 81, -1, -1, -1, -1, -1, -1, -1, -1, -1, -1, -1, -1, -1, -1, -1, -1, -1, -1, -1, -1, -1, -1, 94, 123, -1, -1, -1, -1, -1, -1, -1, -1, -1, -1, -1, -1, -1, -1, -1, -1, -1, -1, -1, -1, -1, -1, 55, 84, -1, -1, -1, -1, -1, -1, -1, -1, -1, -1, -1, -1, -1, -1, -1, -1, -1, -1, -1, -1, -1, -1, 53, 63, -1, -1, -1, -1, -1, -1, -1, -1, -1, -1, -1, -1, -1, -1, -1, -1, -1, -1, -1, -1, -1, -1, 118, 128, -1, -1, -1, -1, -1, -1, -1, -1, -1, -1, -1, -1, -1, -1, -1, -1, -1, -1, -1, -1, -1, -1, 1, 37, -1, -1, -1, -1, -1, -1, -1, -1, -1, -1, -1, -1, -1, -1, -1, -1, -1, -1, -1, -1, -1, -1, 0, 95, 50, 62, -1, -1, -1, -1, -1, -1, -1, -1, -1, -1, -1, -1, -1, -1, -1, -1, -1, -1, -1, -1, 15, 21, 111, 103, -1, -1, -1, -1, -1, -1, -1, -1, -1, -1, -1, -1, -1, -1, -1, -1, -1, -1, -1, -1, 16, 52, 107, 124, -1, -1, -1, -1, -1, -1, -1, -1, -1, -1, -1, -1, -1, -1, -1, -1, -1, -1, -1, -1, 74, 29, 108, -1, -1, -1, -1, -1, -1, -1, -1, -1, -1, -1, -1, -1, -1, -1, -1, -1, -1, 61, -1, -1, 135, 12, -1, -1, -1, -1, -1, -1, -1, -1, -1, -1, -1, -1, -1, -1, -1, -1, -1, -1, 20, 30, -1, 43, 64, 105, 93, 126, 100, -1, -1, -1, -1, -1, -1, -1, -1, -1, -1, -1, -1, -1, -1, -1, 28, 131, 75, 34, 78, 134, 51, 106, 26, -1, -1, -1, -1, 114, 82, -1, -1, -1, -1, -1, -1, -1, -1, -1, -1, 57, 110, 90, 56, 23, 11, 73, 96, 116, 112, -1, -1, 92, 13, 36, -1, -1, -1, -1, -1, -1, -1, 89, 76, 25, 67, 79, 88, -1, 65, 39, 113, 27, 66, 72, 46, 10, 24, 19, 87, 18, 40, 69, 38, 7, 137, 97, 3, 54, 130, 125, -1],
  "n2c": [359, 335, 18, 571, 14, 71, 168, 568, 8, 215, 560, 529, 456, 537, 6, 383, 407, 5, 564, 562, 475, 384, 167, 528, 561, 548, 507, 556, 499, 432, 476, 193, 47, 3, 502, 42, 538, 336, 567, 554, 565, 44, 4, 478, 27, 48, 559, 10, 15, 67, 361, 505, 408, 287, 572, 263, 527, 524, 66, 51, 22, 452, 362, 288, 479, 553, 557, 549, 96, 566, 2, 191, 558, 530, 431, 501, 547, 16, 503, 550, 17, 216, 513, 192, 264, 19, 45, 563, 551, 546, 526, 20, 536, 481, 239, 360, 531, 570, 120, 1, 483, 33, 30, 386, 9, 480, 506, 409, 433, 26, 525, 385, 533, 555, 512, 40, 532, 91, 311, 7, 72, 13, 41, 240, 410, 574, 482, 95, 312, 144, 573, 500, 12, 43, 504, 455, 21, 569, 68, 24]
}
